{
  "site": "micromobilitate.ro",
  "date": "2026-04-08",
  "fetched_at": "2026-04-08T13:36:54.863966+00:00",
  "analysis": {
    "total": 96,
    "in_stock": 55,
    "out_of_stock": 41,
    "missing_description_count": 0,
    "missing_description": []
  },
  "product_ids": [
    1193,
    1191,
    1189,
    1187,
    1185,
    1180,
    609,
    608,
    607,
    606,
    600,
    599,
    219,
    208,
    207,
    206,
    205,
    204,
    203,
    202,
    201,
    200,
    199,
    198,
    196,
    195,
    194,
    193,
    192,
    605,
    604,
    603,
    602,
    601,
    585,
    584,
    583,
    582,
    581,
    566,
    565,
    564,
    563,
    550,
    549,
    548,
    547,
    546,
    545,
    544,
    543,
    522,
    521,
    514,
    513,
    498,
    497,
    496,
    495,
    494,
    470,
    469,
    468,
    458,
    457,
    456,
    431,
    430,
    429,
    402,
    401,
    374,
    373,
    352,
    351,
    350,
    317,
    316,
    286,
    285,
    254,
    253,
    252,
    220,
    218,
    217,
    216,
    215,
    214,
    213,
    212,
    211,
    210,
    209,
    197,
    191
  ]
}